zorg/__init__.py
zorg/py.typed
zorg/app/__init__.py
zorg/app/__main__.py
zorg/app/config.py
zorg/app/runners/__init__.py
zorg/app/runners/_run_action.py
zorg/app/runners/_run_compile.py
zorg/app/runners/_run_db.py
zorg/app/runners/_run_edit.py
zorg/app/runners/_run_file.py
zorg/app/runners/_run_note.py
zorg/app/runners/_run_query.py
zorg/app/runners/_run_template.py
zorg/app/runners/_runners.py
zorg/domain/__init__.py
zorg/domain/types.py
zorg/domain/messages/__init__.py
zorg/domain/messages/commands.py
zorg/domain/messages/events.py
zorg/domain/models/__init__.py
zorg/domain/models/_page.py
zorg/domain/models/_query.py
zorg/grammar/CommonLexerRules.g4
zorg/grammar/ZorgFile.g4
zorg/grammar/ZorgQuery.g4
zorg/grammar/__init__.py
zorg/grammar/zorg_file/ZorgFile.interp
zorg/grammar/zorg_file/ZorgFile.tokens
zorg/grammar/zorg_file/ZorgFileLexer.interp
zorg/grammar/zorg_file/ZorgFileLexer.py
zorg/grammar/zorg_file/ZorgFileLexer.tokens
zorg/grammar/zorg_file/ZorgFileListener.py
zorg/grammar/zorg_file/ZorgFileParser.py
zorg/grammar/zorg_file/__init__.py
zorg/grammar/zorg_query/ZorgQuery.interp
zorg/grammar/zorg_query/ZorgQuery.tokens
zorg/grammar/zorg_query/ZorgQueryLexer.interp
zorg/grammar/zorg_query/ZorgQueryLexer.py
zorg/grammar/zorg_query/ZorgQueryLexer.tokens
zorg/grammar/zorg_query/ZorgQueryListener.py
zorg/grammar/zorg_query/ZorgQueryParser.py
zorg/grammar/zorg_query/__init__.py
zorg/service/__init__.py
zorg/service/file_groups.py
zorg/service/handlers.py
zorg/service/messagebus.py
zorg/service/note_utils.py
zorg/service/templates.py
zorg/service/compiler/__init__.py
zorg/service/compiler/_api.py
zorg/service/compiler/_file_compiler.py
zorg/service/compiler/_query_compiler.py
zorg/service/swog/__init__.py
zorg/service/swog/_executor.py
zorg/service/swog/_refresh_zoq_file.py
zorg/service/swog/_saved_queries.py
zorg/shared/__init__.py
zorg/shared/common.py
zorg/shared/dates.py
zorg/storage/__init__.py
zorg/storage/file/__init__.py
zorg/storage/file/_manager.py
zettel_org-0.8.0.dist-info/METADATA
zettel_org-0.8.0.dist-info/WHEEL
zettel_org-0.8.0.dist-info/entry_points.txt
zettel_org-0.8.0.dist-info/top_level.txt
zettel_org-0.8.0.dist-info/RECORD
