Metadata-Version: 2.1
Name: zettel-org
Version: 0.8.0
Summary: The zettel note manager of the future.
Home-page: https://github.com/bbugyi200/zorg
Author: Bryan M Bugyi
Author-email: bryanbugyi34@gmail.com
License: MIT license
Classifier: Development Status :: 3 - Alpha
Classifier: Intended Audience :: Developers
Classifier: License :: OSI Approved :: MIT License
Classifier: Natural Language :: English
Classifier: Programming Language :: Python :: 3
Classifier: Programming Language :: Python :: 3.9
Classifier: Programming Language :: Python :: 3.10
Classifier: Programming Language :: Python :: 3.11
Classifier: Programming Language :: Python :: 3.12
Requires-Python: >=3.9
Requires-Dist: antlr4-python3-runtime ~=4.13
Requires-Dist: bolton-clack ~=0.3.12
Requires-Dist: bolton-logrus ~=0.1.1
Requires-Dist: bolton-typist ~=0.2.0
Requires-Dist: jinja2
Requires-Dist: python-dateutil ~=2.9
Requires-Dist: rich ~=13.7
Requires-Dist: sqlmodel ~=0.0.16
Requires-Dist: tqdm ~=4.66
Requires-Dist: vimala ~=0.2.0
